tests/__init__.py
tests/test_data.py
tests/test_evaluation.py
tests/test_utils.py
torchkge/__init__.py
torchkge/data_structures.py
torchkge/evaluation.py
torchkge/exceptions.py
torchkge/inference.py
torchkge/sampling.py
torchkge/models/__init__.py
torchkge/models/bilinear.py
torchkge/models/deep.py
torchkge/models/interfaces.py
torchkge/models/translation.py
torchkge/utils/__init__.py
torchkge/utils/data.py
torchkge/utils/data_redundancy.py
torchkge/utils/datasets.py
torchkge/utils/dissimilarities.py
torchkge/utils/losses.py
torchkge/utils/modeling.py
torchkge/utils/operations.py
torchkge/utils/pretrained_models.py
torchkge/utils/training.py
torchkge-0.17.7.dist-info/LICENSE
torchkge-0.17.7.dist-info/METADATA
torchkge-0.17.7.dist-info/WHEEL
torchkge-0.17.7.dist-info/top_level.txt
torchkge-0.17.7.dist-info/RECORD
