Metadata-Version: 2.1
Name: torchkge
Version: 0.17.7
Summary: Knowledge Graph embedding in Python and PyTorch.
Home-page: https://github.com/torchkge-team/torchkge
Author: TorchKGE Developers
Author-email: aboschin@enst.fr
License: BSD license
Keywords: torchkge
Classifier: Development Status :: 2 - Pre-Alpha
Classifier: Intended Audience :: Developers
Classifier: License :: OSI Approved :: BSD License
Classifier: Natural Language :: English
Classifier: Programming Language :: Python :: 3.8
Classifier: Programming Language :: Python :: 3.9
Classifier: Programming Language :: Python :: 3.10
License-File: LICENSE
Requires-Dist: torch (>=1.2.0)
Requires-Dist: tqdm (>=4.64)
Requires-Dist: pandas (>=1.4)
Requires-Dist: numpy (>=1.22)
